yplan_logging_utils/__init__.py
yplan_logging_utils/formatters.py
yplan_logging_utils-1.0.1.dist-info/DESCRIPTION.rst
yplan_logging_utils-1.0.1.dist-info/METADATA
yplan_logging_utils-1.0.1.dist-info/RECORD
yplan_logging_utils-1.0.1.dist-info/WHEEL
yplan_logging_utils-1.0.1.dist-info/metadata.json
yplan_logging_utils-1.0.1.dist-info/top_level.txt
