Metadata-Version: 2.0
Name: yplan-logging-utils
Version: 1.0.1
Summary: Utilities we use for logging.
Home-page: https://github.com/YPlan/yplan-logging-utils
Author: YPlan
Author-email: adam@yplanapp.com
License: ISCL
Keywords: Logging,YPlan
Platform: UNKNOWN
Classifier: Development Status :: 5 - Production/Stable
Classifier: Intended Audience :: Developers
Classifier: License :: OSI Approved :: ISC License (ISCL)
Classifier: Operating System :: OS Independent
Classifier: Programming Language :: Python :: 2
Classifier: Programming Language :: Python :: 2.7
Classifier: Programming Language :: Python :: 3
Classifier: Programming Language :: Python :: 3.4
Classifier: Programming Language :: Python :: 3.5
Classifier: Programming Language :: Python
Classifier: Topic :: System :: Logging
Requires-Dist: six (>=1.5.0)
